jiebanlp/__init__.py
jiebanlp/constant.py
jiebanlp/manager.py
jiebanlp/predict.py
jiebanlp/scheduler.py
jiebanlp/service.py
jiebanlp-3.0.0.dist-info/LICENSE
jiebanlp-3.0.0.dist-info/METADATA
jiebanlp-3.0.0.dist-info/WHEEL
jiebanlp-3.0.0.dist-info/top_level.txt
jiebanlp-3.0.0.dist-info/RECORD
