Metadata-Version: 2.1
Name: jiebanlp
Version: 3.0.0
Summary: A short description of your package
Home-page: https://github.com/
Author: xl
Author-email: 123456@qq.com
License: UNKNOWN
Platform: UNKNOWN
Classifier: Programming Language :: Python :: 3
Classifier: License :: OSI Approved :: MIT License
License-File: LICENSE
Requires-Dist: jieba
Requires-Dist: Flask
Requires-Dist: APScheduler
Requires-Dist: mysql-connector-python
